<?xml version="1.0" encoding="UTF-8"?>
<objects serializationModel="Studio.02.02.00">
	<object class="EncodingSetting" id="{b32c8388-3762-4374-91af-6f1d841fec82}">
		<property name="encodingFormat">
			<value>3</value>
		</property>
		<property name="quality">
			<value>37</value>
		</property>
		<relationship name="platform">
			<destination>{5eb80137-5ed9-46c3-b3e0-8fc2b3a28293}</destination>
		</relationship>
		<relationship name="encodable">
			<destination>{5eb80137-5ed9-46c3-b3e0-8fc2b3a28293}</destination>
		</relationship>
	</object>
</objects>
